pytest_responses.py
pytest3_responses-0.5.0.dist-info/LICENSE
pytest3_responses-0.5.0.dist-info/METADATA
pytest3_responses-0.5.0.dist-info/WHEEL
pytest3_responses-0.5.0.dist-info/entry_points.txt
pytest3_responses-0.5.0.dist-info/top_level.txt
pytest3_responses-0.5.0.dist-info/RECORD
