Metadata-Version: 2.1
Name: pytest3-responses
Version: 0.5.0
Summary: py.test integration for responses
Home-page: https://github.com/getsentry/pytest-responses
Author: David Cramer
Author-email: dcramer@gmail.com
License: Apache 2.0
Platform: UNKNOWN
Classifier: Intended Audience :: Developers
Classifier: Intended Audience :: System Administrators
Classifier: Operating System :: OS Independent
Classifier: Programming Language :: Python :: 2
Classifier: Programming Language :: Python :: 3
Classifier: Topic :: Software Development
Classifier: Framework :: Pytest
License-File: LICENSE
Requires-Dist: responses
Requires-Dist: pytest (>=2.5)
Provides-Extra: tests
Requires-Dist: flake8 ; extra == 'tests'
